sage_blog/__init__.py
sage_blog/admin/__init__.py
sage_blog/admin/category.py
sage_blog/admin/faq.py
sage_blog/admin/filters/__init__.py
sage_blog/admin/filters/category.py
sage_blog/admin/post.py
sage_blog/admin/tag.py
sage_blog/apps.py
sage_blog/filters/__init__.py
sage_blog/filters/post.py
sage_blog/locale/ar/LC_MESSAGES/django.po
sage_blog/locale/en/LC_MESSAGES/django.po
sage_blog/locale/fa/LC_MESSAGES/django.po
sage_blog/management/__init__.py
sage_blog/management/commands/__init__.py
sage_blog/management/commands/generate_blog_data.py
sage_blog/migrations/0001_initial.py
sage_blog/migrations/0002_post_video.py
sage_blog/migrations/__init__.py
sage_blog/models/__init__.py
sage_blog/models/category.py
sage_blog/models/faq.py
sage_blog/models/post.py
sage_blog/models/tag.py
sage_blog/repository/__init__.py
sage_blog/repository/generator/__init__.py
sage_blog/repository/generator/data_generator.py
sage_blog/repository/managers/__init__.py
sage_blog/repository/managers/category.py
sage_blog/repository/managers/post.py
sage_blog/repository/managers/tag.py
sage_blog/repository/queryset/__init__.py
sage_blog/repository/queryset/category.py
sage_blog/repository/queryset/post.py
sage_blog/repository/queryset/tag.py
sage_blog/resources/__init__.py
sage_blog/resources/category.py
sage_blog/resources/faq.py
sage_blog/resources/post.py
sage_blog/resources/tag.py
sage_blog/settings/__init__.py
sage_blog/settings/check.py
sage_blog/tests/__init__.py
sage_blog/tests/conftest.py
sage_blog/tests/factories.py
sage_blog/tests/repository/__init__.py
sage_blog/tests/repository/test_category_dal.py
sage_blog/tests/repository/test_post_dal.py
sage_blog/tests/repository/test_tag_dal.py
sage_blog/translation/__init__.py
sage_blog/translation/category.py
sage_blog/translation/faq.py
sage_blog/translation/post.py
sage_blog/translation/tag.py
sage_blog/utils/__init__.py
sage_blog/utils/import_export/__init__.py
sage_blog/utils/import_export/errors.py
django_sage_blog-0.2.11.dist-info/LICENSE
django_sage_blog-0.2.11.dist-info/METADATA
django_sage_blog-0.2.11.dist-info/WHEEL
django_sage_blog-0.2.11.dist-info/RECORD
